tako/__init__.py
tako/client.py
tako/types/__init__.py
tako/types/common/__init__.py
tako/types/common/errors.py
tako/types/common/exceptions.py
tako/types/knowledge_search/__init__.py
tako/types/knowledge_search/types.py
tako/types/visualize/__init__.py
tako/types/visualize/types.py
tako_sdk-0.1.41.dist-info/METADATA
tako_sdk-0.1.41.dist-info/WHEEL
tako_sdk-0.1.41.dist-info/top_level.txt
tako_sdk-0.1.41.dist-info/RECORD
