Metadata-Version: 2.4
Name: tako-sdk
Version: 0.1.41
Summary: A Python SDK for interacting with the Tako API
Author: Tako
Author-email: support@trytako.com
License: MIT
Requires-Python: >=3.9
Requires-Dist: pydantic>=2.8.2
Requires-Dist: pytest>=7.4.3
Requires-Dist: requests>=2.32.3
Requires-Dist: httpx>=0.25.1
Requires-Dist: pytest-asyncio>=0.21.1
Dynamic: author
Dynamic: author-email
Dynamic: description
Dynamic: description-content-type
Dynamic: license
Dynamic: requires-dist
Dynamic: requires-python
Dynamic: summary
